MANIFEST.in
README.rst
setup.py
django_reminders.egg-info/PKG-INFO
django_reminders.egg-info/SOURCES.txt
django_reminders.egg-info/dependency_links.txt
django_reminders.egg-info/not-zip-safe
django_reminders.egg-info/top_level.txt
reminders/__init__.py
reminders/models.py
reminders/urls.py
reminders/views.py
reminders/templatetags/__init__.py
reminders/templatetags/reminders_tags.py