Metadata-Version: 1.0
Name: django-reminders
Version: 0.2
Summary: a user reminder app for site builders to guide users through completion of activities
Home-page: https://github.com/eldarion/django-reminders
Author: paltman@eldarion.com
Author-email: 2011, Eldarion
License: BSD
Platform: UNKNOWN
Classifier: Development Status :: 3 - Alpha
Classifier: Environment :: Web Environment
Classifier: Intended Audience :: Developers
Classifier: License :: OSI Approved :: BSD License
Classifier: Operating System :: OS Independent
Classifier: Programming Language :: Python
Classifier: Framework :: Django
